{
  "title": "Pluto / StreamlinePro",
  "subtitle": "Sitemap — every screen, modal, auth page, and how they link",
  "roles": [
    { "id": "manager", "name": "Manager", "icon": "🧑‍💼", "color": "#7aa2ff" },
    { "id": "dispatcher", "name": "Dispatcher", "icon": "📋", "color": "#22c55e" },
    { "id": "worker", "name": "Worker", "icon": "🛠️", "color": "#f59e0b" },
    { "id": "admin", "name": "Platform admin", "icon": "👑", "color": "#a855f7" },
    { "id": "public", "name": "Public / customer", "icon": "👤", "color": "#e879f9" }
  ],
  "groups": [
    { "id": "operations", "name": "Daily ops", "color": "#7aa2ff" },
    { "id": "bookings", "name": "Bookings", "color": "#3b82f6" },
    { "id": "customers", "name": "Customers + messaging", "color": "#06b6d4" },
    { "id": "catalog", "name": "Catalog + offers", "color": "#14b8a6" },
    { "id": "money", "name": "Earnings + payments", "color": "#22c55e" },
    { "id": "insights", "name": "Insights + audit", "color": "#facc15" },
    { "id": "comms", "name": "Email templates", "color": "#f97316" },
    { "id": "team", "name": "Team", "color": "#f59e0b" },
    { "id": "admin", "name": "Platform admin", "color": "#a855f7" },
    { "id": "account", "name": "Account / settings", "color": "#94a3b8" },
    { "id": "auth", "name": "Auth", "color": "#ef4444" },
    { "id": "public", "name": "Public web", "color": "#e879f9" }
  ],
  "screens": [
    {
      "id": "pulse",
      "name": "Pulse",
      "kind": "tab",
      "group": "operations",
      "path": "src/screens/PulseScreen.tsx",
      "roles": ["manager", "dispatcher"],
      "components": ["KPI cards (revenue, bookings, conversions)", "DateField picker", "Period selector", "Heatmap", "LineChart", "Sparkline", "Export button"],
      "navTo": ["board", "schedule"]
    },
    {
      "id": "board",
      "name": "Board (Kanban)",
      "kind": "tab",
      "group": "operations",
      "path": "src/screens/DashboardScreen.tsx",
      "roles": ["manager", "dispatcher"],
      "components": ["Kanban columns (New/Consultation/Dispatched/Paid/Completed)", "DraggableCard", "SearchBar", "StatusPill", "CommunicationsRail"],
      "navTo": ["booking-detail", "booking-new", "customers", "companies"]
    },
    {
      "id": "my-jobs",
      "name": "My Jobs",
      "kind": "tab",
      "group": "operations",
      "path": "src/screens/MyAppointmentsScreen.tsx",
      "roles": ["worker", "manager", "dispatcher"],
      "components": ["Status tabs (Dispatched/Paid/Completed/All)", "BookingRow", "EmptyState", "RefreshControl"],
      "navTo": ["booking-detail", "booking-complete"]
    },
    {
      "id": "schedule",
      "name": "Schedule",
      "kind": "tab",
      "group": "operations",
      "path": "src/screens/ScheduleScreen.tsx",
      "roles": ["manager", "dispatcher", "worker"],
      "components": ["Month calendar", "Agenda view", "BookingRow", "DateNavigation", "TimeDisplay"],
      "navTo": ["schedule-blocks", "booking-detail"]
    },
    {
      "id": "dispatch",
      "name": "Dispatch",
      "kind": "screen",
      "group": "operations",
      "path": "src/screens/DispatchScreen.tsx",
      "roles": ["dispatcher"],
      "components": ["BookingsList", "UserPicker", "WorkerPicker", "MapPin", "StatusPill"],
      "navTo": ["booking-detail", "booking-new"]
    },
    {
      "id": "activity",
      "name": "Activity feed",
      "kind": "screen",
      "group": "insights",
      "path": "src/screens/AuditFeedScreen.tsx",
      "roles": ["manager"],
      "components": ["AuditFeed timeline", "ActivityIcon", "Timestamp", "UserAction"],
      "navTo": ["booking-detail", "customer-detail"]
    },
    {
      "id": "booking-detail",
      "name": "Booking detail",
      "kind": "screen",
      "group": "bookings",
      "path": "src/screens/BookingDetailScreen.tsx",
      "roles": ["manager", "dispatcher", "worker"],
      "components": ["BookingTitle editor", "LocationEditor", "DateTimeField", "RelationField (customer/manager/workers)", "BookingItemsEditor", "ActivityFeed", "BookingPhotos", "StatusPill", "CompleteButton"],
      "navTo": ["customer-detail", "offer-detail", "booking-edit", "booking-complete"]
    },
    {
      "id": "booking-new",
      "name": "New booking",
      "kind": "screen",
      "group": "bookings",
      "path": "src/screens/BookingNewScreen.tsx",
      "roles": ["dispatcher", "manager"],
      "components": ["CustomerPicker (with create inline)", "LocationSelector", "ProductPicker", "DateField", "TimeField", "BookingItemsEditor"],
      "navTo": ["booking-detail"]
    },
    {
      "id": "booking-edit",
      "name": "Edit booking",
      "kind": "screen",
      "group": "bookings",
      "path": "src/screens/BookingEditScreen.tsx",
      "roles": ["dispatcher", "manager"],
      "components": ["TitleEditor", "DateTimeField", "AddressEditor", "ItemsEditor", "PrimaryButton"]
    },
    {
      "id": "booking-complete",
      "name": "Complete booking",
      "kind": "screen",
      "group": "bookings",
      "path": "src/screens/CompleteBookingScreen.tsx",
      "roles": ["dispatcher", "manager", "worker"],
      "components": ["ChecklistReview", "PhotoCapture", "SignaturePad", "CompleteButton"]
    },
    {
      "id": "booking-form-editor",
      "name": "Booking form builder",
      "kind": "screen",
      "group": "admin",
      "path": "src/screens/BookingFormEditorScreen.tsx",
      "roles": ["admin"],
      "components": ["FormFieldsList", "FieldTypeSelector", "FieldEditor", "PreviewPane", "SaveButton"]
    },
    {
      "id": "customers",
      "name": "Customers",
      "kind": "tab",
      "group": "customers",
      "path": "src/screens/CustomersScreen.tsx",
      "roles": ["dispatcher", "manager"],
      "components": ["SearchInput", "FilterButton", "CustomerTable (desktop) / FlatList (mobile)", "MultiSelectModal", "CompanyFilter", "VerticalFilter"],
      "navTo": ["customer-detail", "customer-new"]
    },
    {
      "id": "customer-detail",
      "name": "Customer detail",
      "kind": "screen",
      "group": "customers",
      "path": "src/screens/CustomerDetailScreen.tsx",
      "roles": ["dispatcher", "manager"],
      "components": ["CustomerInfo card", "LocationsList", "BookingsTable", "ContactFields", "DeleteButton", "EditButton"],
      "navTo": ["booking-detail", "customer-edit", "communication-new"]
    },
    {
      "id": "customer-new",
      "name": "New customer",
      "kind": "screen",
      "group": "customers",
      "path": "src/screens/CustomerNewScreen.tsx",
      "roles": ["dispatcher", "manager"],
      "components": ["FormFields (name, email, phone, address)", "PrimaryButton"],
      "navTo": ["customer-detail"]
    },
    {
      "id": "customer-edit",
      "name": "Edit customer",
      "kind": "screen",
      "group": "customers",
      "path": "src/screens/CustomerEditScreen.tsx",
      "roles": ["dispatcher", "manager"],
      "components": ["FormFields", "PrimaryButton", "DeleteButton"]
    },
    {
      "id": "inbox",
      "name": "Inbox",
      "kind": "tab",
      "group": "customers",
      "path": "src/screens/InboxScreen.tsx",
      "roles": ["manager", "dispatcher", "worker"],
      "components": ["ThreadList", "SearchBar", "UnreadBadge", "LastMessage preview", "TimeAgo", "StatusPill"],
      "navTo": ["thread"]
    },
    {
      "id": "thread",
      "name": "Message thread",
      "kind": "screen",
      "group": "customers",
      "path": "src/screens/ThreadScreen.tsx",
      "roles": ["manager", "dispatcher", "worker"],
      "components": ["MessageList", "Compose input", "SendButton", "AttachmentButton", "UserAvatar"],
      "navTo": ["booking-detail"]
    },
    {
      "id": "communications",
      "name": "Communication detail",
      "kind": "screen",
      "group": "customers",
      "path": "src/screens/CommunicationDetailScreen.tsx",
      "roles": ["dispatcher", "manager"],
      "components": ["CommunicationBody", "RecipientsList", "LinkedBooking", "Metadata"],
      "navTo": ["booking-detail", "customer-detail"]
    },
    {
      "id": "communication-new",
      "name": "New communication",
      "kind": "screen",
      "group": "customers",
      "path": "src/screens/CommunicationNewScreen.tsx",
      "roles": ["dispatcher", "manager"],
      "components": ["RecipientPicker", "BodyEditor", "TemplateSelector", "SendButton"]
    },
    {
      "id": "products",
      "name": "Products",
      "kind": "screen",
      "group": "catalog",
      "path": "src/screens/ProductsScreen.tsx",
      "roles": ["manager"],
      "components": ["ProductGrid", "ProductCard", "SearchBar", "PrimaryImage", "PriceDisplay"],
      "navTo": ["product-detail"]
    },
    {
      "id": "product-detail",
      "name": "Product detail",
      "kind": "screen",
      "group": "catalog",
      "path": "src/screens/ProductDetailScreen.tsx",
      "roles": ["manager"],
      "components": ["ProductImage", "PriceEditor", "DescriptionField", "ActiveToggle", "DeleteButton"]
    },
    {
      "id": "offers",
      "name": "Offers",
      "kind": "screen",
      "group": "catalog",
      "path": "src/screens/OffersScreen.tsx",
      "roles": ["manager"],
      "components": ["StatusTabs (all/draft/sent/viewed/approved/declined)", "OfferRow", "TotalDisplay", "ExportButton", "CreateFAB"],
      "navTo": ["offer-detail", "offer-builder"]
    },
    {
      "id": "offer-builder",
      "name": "Offer builder",
      "kind": "screen",
      "group": "catalog",
      "path": "src/screens/OfferBuilderScreen.tsx",
      "roles": ["manager"],
      "components": ["CustomerNameInput", "ItemsTable (with add/remove)", "DiscountLines", "ChargeLines", "TotalDisplay", "SubmitButton"],
      "navTo": ["offer-detail"]
    },
    {
      "id": "offer-detail",
      "name": "Offer detail",
      "kind": "screen",
      "group": "catalog",
      "path": "src/screens/OfferDetailScreen.tsx",
      "roles": ["manager"],
      "components": ["CustomerInfo", "ItemsDisplay", "DiscountDisplay", "ChargeDisplay", "StatusPill", "SendButton", "ApprovalButtons"],
      "navTo": ["booking-detail"]
    },
    {
      "id": "checklists",
      "name": "Checklists",
      "kind": "screen",
      "group": "catalog",
      "path": "src/screens/ChecklistEditorScreen.tsx",
      "roles": ["manager"],
      "components": ["ChecklistList", "CreateButton", "EditButton", "ChecklistRow"],
      "navTo": ["checklist-view"]
    },
    {
      "id": "checklist-view",
      "name": "View / execute checklist",
      "kind": "screen",
      "group": "catalog",
      "path": "src/screens/ChecklistScreen.tsx",
      "roles": ["manager", "dispatcher", "worker"],
      "components": ["ChecklistItems", "Checkboxes", "ItemComments", "ProgressBar", "SaveButton"]
    },
    {
      "id": "earnings",
      "name": "Earnings",
      "kind": "tab",
      "group": "money",
      "path": "src/screens/WorkerEarningsScreen.tsx",
      "roles": ["worker"],
      "components": ["EarningsSummary card", "EarningsTable", "PayoutStatusBadge", "RoleLabel"],
      "navTo": ["booking-detail", "payments"]
    },
    {
      "id": "payments",
      "name": "Payments",
      "kind": "screen",
      "group": "money",
      "path": "src/screens/PaymentsScreen.tsx",
      "roles": ["manager", "dispatcher", "worker"],
      "components": ["PaymentsList", "StatusFilter", "InvoiceNumber", "AmountDisplay", "DownloadButton"]
    },
    {
      "id": "reviews",
      "name": "Customer reviews",
      "kind": "screen",
      "group": "insights",
      "path": "src/screens/ReviewsScreen.tsx",
      "roles": ["manager"],
      "components": ["RatingOverview card", "StarRating display", "ReviewDistributionChart", "ReviewList", "AverageRating"]
    },
    {
      "id": "emails",
      "name": "Email templates",
      "kind": "screen",
      "group": "comms",
      "path": "src/screens/EmailManagementScreen.tsx",
      "roles": ["manager"],
      "components": ["TemplateList", "SearchBar", "CreateButton", "TemplateRow"],
      "navTo": ["email-template-edit"]
    },
    {
      "id": "email-template-edit",
      "name": "Edit email template",
      "kind": "screen",
      "group": "comms",
      "path": "src/screens/EmailTemplateEditScreen.tsx",
      "roles": ["manager"],
      "components": ["SubjectInput", "BodyEditor", "VariableInsertPanel", "PreviewPane", "SaveButton"]
    },
    {
      "id": "team",
      "name": "Team",
      "kind": "screen",
      "group": "team",
      "path": "src/screens/TeamScreen.tsx",
      "roles": ["manager"],
      "components": ["UserList", "SearchBar", "RoleFilter", "UserRow", "ResetPasswordButton", "DeleteButton", "UserFormModal"],
      "navTo": ["user-availability", "team-form"]
    },
    {
      "id": "team-form",
      "name": "Add / edit user",
      "kind": "modal",
      "group": "team",
      "path": "src/screens/TeamScreen.tsx — UserFormModal",
      "roles": ["manager"],
      "components": ["first_name input", "last_name input", "email input", "phone input", "role dropdown", "Save button (returns meta.temp_password)"]
    },
    {
      "id": "user-availability",
      "name": "User availability",
      "kind": "screen",
      "group": "team",
      "path": "src/screens/UserAvailabilityScreen.tsx",
      "roles": ["manager"],
      "components": ["AvailabilityCalendar", "TimeSlots", "BlockEditor", "PrimaryButton"]
    },
    {
      "id": "schedule-blocks",
      "name": "Schedule blocks",
      "kind": "screen",
      "group": "team",
      "path": "src/screens/ScheduleBlocksScreen.tsx",
      "roles": ["manager"],
      "components": ["BlocksList", "DateHeader", "CreateModal", "EditModal", "DeleteButton"]
    },
    {
      "id": "companies",
      "name": "Companies",
      "kind": "screen",
      "group": "admin",
      "path": "src/screens/CompaniesScreen.tsx",
      "roles": ["admin"],
      "components": ["CompanyTable", "SearchBar", "CreateButton", "CompanyRow", "ActiveBadge"],
      "navTo": ["company-detail", "company-form"]
    },
    {
      "id": "company-detail",
      "name": "Company detail",
      "kind": "screen",
      "group": "admin",
      "path": "src/screens/CompanyDetailScreen.tsx",
      "roles": ["admin"],
      "components": ["CompanyInfo card", "LocationsList (with LocationFormModal)", "ProductsCatalog", "MembersList", "ApplyVerticalCatalogButton", "DeleteButton"],
      "navTo": ["company-form", "board", "team", "product-detail", "security-users"]
    },
    {
      "id": "company-form",
      "name": "Create / edit company",
      "kind": "screen",
      "group": "admin",
      "path": "src/screens/CompanyFormScreen.tsx",
      "roles": ["admin"],
      "components": ["NameInput", "SlugInput", "DescriptionField", "VerticalPicker", "ActiveToggle", "PrimaryButton"],
      "navTo": ["company-detail"]
    },
    {
      "id": "verticals",
      "name": "Verticals",
      "kind": "screen",
      "group": "admin",
      "path": "src/screens/VerticalsScreen.tsx",
      "roles": ["admin"],
      "components": ["VerticalList", "SearchBar", "CreateButton", "VerticalRow", "VerticalEditorModal"],
      "navTo": ["service-areas"]
    },
    {
      "id": "service-areas",
      "name": "Service areas (ZIP routing)",
      "kind": "screen",
      "group": "admin",
      "path": "src/screens/ZipRoutingScreen.tsx",
      "roles": ["admin"],
      "components": ["ZIPTable", "CompanySelector", "VerticalFilter", "CoverageMap", "EditButton"]
    },
    {
      "id": "security-users",
      "name": "Platform users",
      "kind": "screen",
      "group": "admin",
      "path": "src/screens/SecurityUsersScreen.tsx",
      "roles": ["admin"],
      "components": ["UserList", "SearchBar", "CompanyFilter", "RoleAssigner", "ResetPasswordModal", "DeleteButton", "EditModal"]
    },
    {
      "id": "security-roles",
      "name": "Roles + permissions",
      "kind": "screen",
      "group": "admin",
      "path": "src/screens/SecurityRolesScreen.tsx",
      "roles": ["admin"],
      "components": ["RolesList", "PermissionsMatrix", "CreateButton", "EditModal", "DeleteButton"]
    },
    {
      "id": "stripe-webhooks",
      "name": "Stripe webhooks",
      "kind": "screen",
      "group": "insights",
      "path": "src/screens/StripeWebhooksScreen.tsx",
      "roles": ["admin"],
      "components": ["WebhooksList", "EventTypeFilter", "TimestampDisplay", "PayloadViewer", "TestButton"]
    },
    {
      "id": "email-activity",
      "name": "Email activity",
      "kind": "screen",
      "group": "insights",
      "path": "src/screens/EmailActivityScreen.tsx",
      "roles": ["admin"],
      "components": ["ActivityLog", "DateRangeFilter", "EventTypeFilter", "UserFilter", "SenderDisplay"]
    },
    {
      "id": "password-audit",
      "name": "Password audit",
      "kind": "screen",
      "group": "insights",
      "path": "src/screens/PasswordAuditScreen.tsx",
      "roles": ["admin"],
      "components": ["AuditLog", "DateRangeFilter", "UserFilter", "ActionType (reset/change)", "Timestamp"]
    },
    {
      "id": "settings",
      "name": "Settings",
      "kind": "tab",
      "group": "account",
      "path": "src/screens/SettingsScreen.tsx",
      "roles": ["manager", "dispatcher", "worker", "admin"],
      "components": ["SettingsMenu", "CompanyName", "WorkspaceInfo", "SignOutButton"],
      "navTo": ["profile", "password", "appearance", "team", "emails", "reviews", "activity", "stripe-webhooks", "email-activity", "password-audit", "verticals", "service-areas", "security-users", "security-roles", "companies", "booking-form-editor"]
    },
    {
      "id": "profile",
      "name": "Profile",
      "kind": "screen",
      "group": "account",
      "path": "src/screens/ProfileScreen.tsx",
      "roles": ["manager", "dispatcher", "worker", "admin"],
      "components": ["UserAvatar", "NameDisplay", "EmailDisplay", "PhoneInput", "UpdateButton"]
    },
    {
      "id": "password",
      "name": "Change password",
      "kind": "screen",
      "group": "account",
      "path": "src/screens/PasswordScreen.tsx",
      "roles": ["manager", "dispatcher", "worker", "admin"],
      "components": ["CurrentPasswordInput", "NewPasswordInput", "ConfirmInput", "StrengthIndicator", "UpdateButton"]
    },
    {
      "id": "appearance",
      "name": "Appearance",
      "kind": "screen",
      "group": "account",
      "path": "src/screens/AppearanceScreen.tsx",
      "roles": ["manager", "dispatcher", "worker", "admin"],
      "components": ["ThemeSelector (light/dark/auto)", "AccentColorPicker", "FontSizeSelector", "PreviewPane"]
    },
    {
      "id": "login",
      "name": "Sign in",
      "kind": "auth",
      "group": "auth",
      "path": "src/screens/LoginScreen.tsx",
      "roles": ["public"],
      "components": ["LogoDisplay", "EmailInput", "PasswordInput", "RememberMeToggle", "SignInButton", "ForgotPasswordLink"],
      "navTo": ["forgot-password", "pulse", "my-jobs"]
    },
    {
      "id": "forgot-password",
      "name": "Forgot password",
      "kind": "auth",
      "group": "auth",
      "path": "src/screens/ForgotPasswordScreen.tsx",
      "roles": ["public"],
      "components": ["EmailInput", "SubmitButton", "BackToLoginLink", "SuccessMessage"],
      "navTo": ["login"]
    },
    {
      "id": "reset-password",
      "name": "Reset password",
      "kind": "auth",
      "group": "auth",
      "path": "src/screens/ResetPasswordScreen.tsx",
      "roles": ["public"],
      "components": ["PasswordInput", "ConfirmInput", "StrengthIndicator", "SubmitButton"],
      "navTo": ["login"]
    },
    {
      "id": "public-booking-funnel",
      "name": "Public booking funnel",
      "kind": "public",
      "group": "public",
      "path": "src/screens/PublicBookingFunnelScreen.tsx",
      "roles": ["public"],
      "components": ["ZIPGate (Step 0)", "ProductSelector (Step 1)", "ContactForm (Step 2)", "AddressForm", "PhotoCapture (Step 3)", "ReviewSummary (Step 4)", "SubmitButton", "OutOfServiceArea fallback"]
    }
  ]
}
